callllm/__init__.py
callllm/base.py
callllm/checkpoint.py
callllm/tasks.py
callllm/worker.py
callllm-0.1.1.dist-info/METADATA
callllm-0.1.1.dist-info/WHEEL
callllm-0.1.1.dist-info/top_level.txt
callllm-0.1.1.dist-info/RECORD
